{"BaseModel.b2e97c51-af5a-4f48-88d9-149fa0d8261e": {"id": "b2e97c51-af5a-4f48-88d9-149fa0d8261e", "created_at": "2022-11-27T17:18:58.345774", "updated_at": "2022-11-27T17:18:58.345846", "name": "My First Model", "my_number": 89, "__class__": "BaseModel"}, "BaseModel.176653fd-145b-4681-9421-593e8ac18a61": {"id": "176653fd-145b-4681-9421-593e8ac18a61", "created_at": "2022-11-27T17:21:28.947749", "updated_at": "2022-11-27T17:21:28.947805", "name": "My_First_Model", "my_number": 89, "__class__": "BaseModel"}, "BaseModel.35a0159c-c60e-47a4-b106-3c24c068cec2": {"id": "35a0159c-c60e-47a4-b106-3c24c068cec2", "created_at": "2022-11-27T17:22:11.147790", "updated_at": "2022-11-27T17:22:11.147798", "name": "My_First_Model", "my_number": 89, "__class__": "BaseModel"}, "BaseModel.119be019-8ae5-4456-a0f8-90826ec8fd88": {"id": "119be019-8ae5-4456-a0f8-90826ec8fd88", "created_at": "2022-11-27T17:22:32.654347", "updated_at": "2022-11-27T17:22:32.654358", "name": "My_First_Model", "my_number": 89, "__class__": "BaseModel"}, "BaseModel.b4de7fde-f371-43ac-8d11-b30c32a34f60": {"id": "b4de7fde-f371-43ac-8d11-b30c32a34f60", "created_at": "2022-11-27T17:25:27.586618", "updated_at": "2022-11-27T17:25:27.586648", "__class__": "BaseModel"}, "BaseModel.9144e533-4a84-4202-b7d4-00dd1380dbeb": {"id": "9144e533-4a84-4202-b7d4-00dd1380dbeb", "created_at": "2022-11-27T17:30:36.722793", "updated_at": "2022-11-27T17:30:36.722829", "__class__": "BaseModel"}, "User.1da3b344-f673-4f5c-bc99-9bb63b1ca487": {"id": "1da3b344-f673-4f5c-bc99-9bb63b1ca487", "created_at": "2022-11-27T17:33:00.347899", "updated_at": "2022-11-27T17:33:00.347910", "first_name": "Betty", "last_name": "Bar", "email": "airbnb@mail.com", "password": "root", "__class__": "User"}, "User.876c02a1-f06c-43ff-8455-be766ed6020e": {"id": "876c02a1-f06c-43ff-8455-be766ed6020e", "created_at": "2022-11-27T17:33:00.348344", "updated_at": "2022-11-27T17:33:00.348352", "first_name": "John", "email": "airbnb2@mail.com", "password": "root", "__class__": "User"}, "User.6415ff19-bab5-4b02-8f54-421c93d1c7f7": {"id": "6415ff19-bab5-4b02-8f54-421c93d1c7f7", "created_at": "2022-11-27T17:33:53.249359", "updated_at": "2022-11-27T17:33:53.249369", "first_name": "Betty", "last_name": "Bar", "email": "airbnb@mail.com", "password": "root", "__class__": "User"}, "User.fd2f4288-1ff8-453c-9f30-bb90cbf01166": {"id": "fd2f4288-1ff8-453c-9f30-bb90cbf01166", "created_at": "2022-11-27T17:33:53.249842", "updated_at": "2022-11-27T17:33:53.249850", "first_name": "John", "email": "airbnb2@mail.com", "password": "root", "__class__": "User"}}